Metadata-Version: 1.0
Name: ncc-pa-elasticsearch
Version: 0.0.1
Summary: PA to ElasticSearch coupler
Home-page: https://github.com/ncc-tools/pa-elasticsearch-coupler
Author: NCC Group
Author-email: UNKNOWN
License: Apache License 2.0
Platform: UNKNOWN
